examples/MNIST Classification Report.html
examples/basic_ml_pipeline.yml
examples/mnist_pipeline.yml
examples/mnist_scripts/create_mnist_report.py
examples/mnist_scripts/evaluate_pytorch_mnist.py
examples/mnist_scripts/fetch_mnist.py
examples/mnist_scripts/preprocess_mnist.py
examples/mnist_scripts/train_pytorch_mnist.py
examples/scripts/evaluate.py
examples/scripts/fetch_data.py
examples/scripts/generate_report.py
examples/scripts/models.py
examples/scripts/preprocess.py
examples/scripts/train_model.py
examples/scripts/validate_data.py
ml_orchestrator/__init__.py
ml_orchestrator/cli.py
ml_orchestrator/config/__init__.py
ml_orchestrator/config/parser.py
ml_orchestrator/config/validator.py
ml_orchestrator/core/__init__.py
ml_orchestrator/core/dag.py
ml_orchestrator/core/pipeline.py
ml_orchestrator/core/state.py
ml_orchestrator/core/task.py
ml_orchestrator/utils/__init__.py
ml_orchestrator/utils/exceptions.py
ml_orchestrator/utils/logging.py
ml_pipeline_orchestrator-0.1.2.dist-info/METADATA
ml_pipeline_orchestrator-0.1.2.dist-info/WHEEL
ml_pipeline_orchestrator-0.1.2.dist-info/entry_points.txt
ml_pipeline_orchestrator-0.1.2.dist-info/top_level.txt
ml_pipeline_orchestrator-0.1.2.dist-info/RECORD
