Metadata-Version: 2.1
Name: ml-pipeline-orchestrator
Version: 0.1.2
Summary: A lightweight ML pipeline orchestrator
Home-page: https://github.com/therrshan/ml-orchestrator
Author: Darshan Rajopadhye
Author-email: Darshan Rajopadhye <rajopadhye.d@northeastern.edu>
License: MIT
Requires-Python: >=3.8
Requires-Dist: PyYAML>=6.0
Requires-Dist: click>=8.0.0
Requires-Dist: colorama>=0.4.0
